bio2bel_mirbase/__init__.py
bio2bel_mirbase/cli.py
bio2bel_mirbase/constants.py
bio2bel_mirbase/download.py
bio2bel_mirbase/manager.py
bio2bel_mirbase/models.py
bio2bel_mirbase/parser.py
bio2bel_mirbase/utils.py
bio2bel_mirbase-0.1.1.dist-info/LICENSE
bio2bel_mirbase-0.1.1.dist-info/METADATA
bio2bel_mirbase-0.1.1.dist-info/WHEEL
bio2bel_mirbase-0.1.1.dist-info/entry_points.txt
bio2bel_mirbase-0.1.1.dist-info/top_level.txt
bio2bel_mirbase-0.1.1.dist-info/zip-safe
bio2bel_mirbase-0.1.1.dist-info/RECORD
